dynamodm/__init__.py
dynamodm/_decorators.py
dynamodm/_exceptions.py
dynamodm/_json.py
dynamodm/_proxy.py
dynamodm/odm.py
dynamodm/utils.py
dynamodm-0.0.4.dist-info/METADATA
dynamodm-0.0.4.dist-info/WHEEL
dynamodm-0.0.4.dist-info/RECORD
